datacorecommon/__init__.py
datacorecommon/_helpers.py
datacorecommon/dataframe/__init__.py
datacorecommon/dataframe/_dataframe.py
datacorecommon/filter/__init__.py
datacorecommon/filter/_filter.py
datacorecommon/inout/__init__.py
datacorecommon/inout/_delta.py
datacorecommon/inout/_jdbc.py
datacorecommon/schedule/__init__.py
datacorecommon/schedule/schedule.py
datacorecommon/transformations/__init__.py
datacorecommon/transformations/_transformations.py
datacorecommon/window/__init__.py
datacorecommon/window/_bag.py
datacorecommon-0.5.0.dist-info/LICENSE.txt
datacorecommon-0.5.0.dist-info/METADATA
datacorecommon-0.5.0.dist-info/WHEEL
datacorecommon-0.5.0.dist-info/top_level.txt
datacorecommon-0.5.0.dist-info/RECORD
