Metadata-Version: 2.1
Name: datacorecommon
Version: 0.5.0
Summary: Wrapper functions for PySpark
Author: Data core team
License: MIT
Keywords: pyspark,databricks
Classifier: Programming Language :: Python :: 3 :: Only
Classifier: License :: OSI Approved :: MIT License
Classifier: Operating System :: OS Independent
Classifier: Development Status :: 4 - Beta
Classifier: Topic :: Software Development
Classifier: Intended Audience :: Developers
Requires-Python: >=3.6
License-File: LICENSE.txt
